flake8_no_json/__init__.py
flake8_no_json/entry.py
flake8_no_json/py.typed
flake8_no_json-0.0.2.dist-info/LICENSE
flake8_no_json-0.0.2.dist-info/METADATA
flake8_no_json-0.0.2.dist-info/WHEEL
flake8_no_json-0.0.2.dist-info/entry_points.txt
flake8_no_json-0.0.2.dist-info/RECORD
