Metadata-Version: 2.1
Name: flake8-no-json
Version: 0.0.2
Summary: flake8 plugin for using json from stdlib
Home-page: https://github.com/blablatdinov/flake8-no-json
License: MIT
Author: Almaz Ilaletdinov
Author-email: a.ilaletdinov@yandex.ru
Requires-Python: >=3.9,<4.0
Classifier: Development Status :: 3 - Alpha
Classifier: Intended Audience :: Developers
Classifier: License :: OSI Approved :: MIT License
Classifier: Operating System :: OS Independent
Classifier: Programming Language :: Python :: 3
Classifier: Programming Language :: Python :: 3.9
Classifier: Programming Language :: Python :: 3.10
Classifier: Programming Language :: Python :: 3.11
Classifier: Programming Language :: Python :: 3.12
Classifier: Topic :: Software Development :: Libraries :: Python Modules
Requires-Dist: flake8 (>=5)
Project-URL: Repository, https://github.com/blablatdinov/flake8-no-json
